smartdoc15_ch1/__init__.py
smartdoc15_ch1/evaluation.py
smartdoc15_ch1/poly_utils.py
smartdoc15_ch1/smartdoc_loader.py
smartdoc15_ch1/smartdoc_loader_v2.py
smartdoc15_ch1-0.8.dist-info/DESCRIPTION.rst
smartdoc15_ch1-0.8.dist-info/METADATA
smartdoc15_ch1-0.8.dist-info/RECORD
smartdoc15_ch1-0.8.dist-info/WHEEL
smartdoc15_ch1-0.8.dist-info/metadata.json
smartdoc15_ch1-0.8.dist-info/top_level.txt
