Metadata-Version: 2.0
Name: smartdoc15-ch1
Version: 0.8
Summary: A Python wrapper for the "computable" version of the SmartDoc 2015 - Challenge 1 dataset.
Home-page: https://github.com/jchazalon/smartdoc15-ch1-pywrapper
Author: Joseph Chazalon
Author-email: joseph.chazalon@lrde.epita.fr
License: MIT
Project-URL: Dataset (original), https://sites.google.com/site/icdar15smartdoc/
Project-URL: Source, https://github.com/jchazalon/smartdoc15-ch1-pywrapper
Project-URL: Documentation, https://github.com/jchazalon/smartdoc15-ch1-pywrapper
Project-URL: Bug Reports, https://github.com/jchazalon/smartdoc15-ch1-pywrapper/issues
Project-URL: Dataset (Python), https://github.com/jchazalon/smartdoc15-ch1-dataset
Keywords: dataset wrapper image_processing computer_vision
Platform: UNKNOWN
Classifier: Development Status :: 4 - Beta
Classifier: Intended Audience :: Science/Research
Classifier: Topic :: Scientific/Engineering :: Image Recognition
Classifier: License :: OSI Approved :: MIT License
Classifier: Programming Language :: Python :: 2
Classifier: Programming Language :: Python :: 2.7
Classifier: Programming Language :: Python :: 3
Classifier: Programming Language :: Python :: 3.4
Classifier: Programming Language :: Python :: 3.5
Classifier: Programming Language :: Python :: 3.6
Classifier: Natural Language :: English
Classifier: Operating System :: OS Independent
Requires-Dist: numpy (>=1.11)
Requires-Dist: pandas (>=0.22)
Requires-Dist: Pillow (>=5.0)
Requires-Dist: Polygon2 (>=2.0)
Requires-Dist: scikit-image (>=0.13)
Requires-Dist: scikit-learn (>=0.18)
Requires-Dist: scipy (>=1.0)
Requires-Dist: six (>=1.0)
